numpretty/__init__.py
numpretty/__version__.py
numpretty/main.py
numpretty-1.0.3.dist-info/LICENSE
numpretty-1.0.3.dist-info/METADATA
numpretty-1.0.3.dist-info/WHEEL
numpretty-1.0.3.dist-info/top_level.txt
numpretty-1.0.3.dist-info/RECORD
