Metadata-Version: 2.1
Name: numpretty
Version: 1.0.3
Summary: Numpretty converts numbers into their human-readable form, efficiently.
Home-page: https://github.com/obfuscatedgenerated/numpretty
Author: obfuscatedgenerated
Author-email: pip@obfuscatedgenerated.ml
License: MIT
Keywords: math,numbers,pretty,human,readable
Platform: UNKNOWN
Classifier: Development Status :: 3 - Alpha
Classifier: Intended Audience :: Developers
Classifier: Topic :: Software Development :: Libraries :: Python Modules
Classifier: License :: OSI Approved :: MIT License
Classifier: Programming Language :: Python :: 3
Classifier: Programming Language :: Python :: 3.4
Classifier: Programming Language :: Python :: 3.5
Classifier: Programming Language :: Python :: 3.6
Classifier: Programming Language :: Python :: 3.7
Classifier: Programming Language :: Python :: 3.8
Classifier: Programming Language :: Python :: 3.9
